extras/__init__.py
extras/divide.py
extras/multiply.py
hbr_samplemodule-0.0.1.dist-info/METADATA
hbr_samplemodule-0.0.1.dist-info/WHEEL
hbr_samplemodule-0.0.1.dist-info/top_level.txt
hbr_samplemodule-0.0.1.dist-info/RECORD
